stencila-2.0.0a26.dist-info/METADATA
stencila-2.0.0a26.dist-info/WHEEL
stencila/__init__.py
stencila/_stencila.pyi
stencila/py.typed
stencila/convert.py
stencila/_stencila.cpython-311-x86_64-linux-gnu.so
stencila-2.0.0a26.dist-info/RECORD
