Metadata-Version: 2.3
Name: stencila
Version: 2.0.0a26
Classifier: Development Status :: 3 - Alpha
Classifier: Intended Audience :: Developers
Classifier: Intended Audience :: Science/Research
Classifier: Intended Audience :: Education
Classifier: Topic :: Software Development
Classifier: License :: OSI Approved :: Apache Software License
Requires-Dist: strenum ==0.4.15 ; python_version < '3.11'
Requires-Dist: beartype ==0.18.5
Requires-Dist: cattrs ==23.2.3
Requires-Dist: stencila-types ==2.0.0a31
Summary: Python SDK for Stencila
Keywords: programmable,reproducible,interactive,documents,python,SDK
Author-email: Nokome Bentley <nokome@stencila.io>
License: Apache-2.0
Requires-Python: >=3.10
Project-URL: Homepage, https://github.com/stencila/stencila/tree/main/python#readme
Project-URL: Repository, https://github.com/stencila/stencila
